bash_runner/__init__.py
bash_runner/__main__.py
bash_runner/colors.py
bash_runner/models.py
bash_runner/printer.py
bash_runner/py.typed
bash_runner/runner.py
bash_runner-0.0.1.dist-info/METADATA
bash_runner-0.0.1.dist-info/WHEEL
bash_runner-0.0.1.dist-info/namespace_packages.txt
bash_runner-0.0.1.dist-info/top_level.txt
bash_runner-0.0.1.dist-info/RECORD
